{
  "id": "transcendance",
  "title": "Transcendance",
  "slug": "transcendance",
  "order": 40,
  "series": "Bleu Cendres",
  "year": "",
  "dimensions": "29 × 29 cm",
  "technique": "Acrylique sur toile",
  "status": "available",
  "featured": true,
  "detailEnabled": true,
  "price": "",
  "description": "L’or qui s’élève au-dessus du bleu — la lumière que l’artiste aime s’approprier pour mieux la restituer.",
  "descriptionLong": "",
  "image": "",
  "images": [],
  "alt": "Petite toile carrée abstraite, bleu profond et or, série Bleu Cendres, 29 × 29 cm.",
  "videoEnabled": false,
  "videoUrl": "",
  "videoProvider": "",
  "videoTitle": "",
  "videoCaption": ""
}
